medvlp/__init__.py
medvlp/py.typed
medvlp-0.1.dist-info/METADATA
medvlp-0.1.dist-info/WHEEL
medvlp-0.1.dist-info/top_level.txt
medvlp-0.1.dist-info/RECORD
