Metadata-Version: 2.1
Name: medvlp
Version: 0.1
Summary: Medical Vision-Language Processing
Home-page: https://github.com/DIAGNijmegen/medvlp
Author: Joeran Bosma, Luc Builtjes
Author-email: Joeran.Bosma@radboudumc.nl
Project-URL: Bug Tracker, https://github.com/DIAGNijmegen/medvlp/issues
Platform: unix
Platform: linux
Platform: osx
Platform: cygwin
Platform: win32
Classifier: Programming Language :: Python :: 3
Classifier: Programming Language :: Python :: 3 :: Only
Classifier: Programming Language :: Python :: 3.6
Classifier: Programming Language :: Python :: 3.7
Classifier: Programming Language :: Python :: 3.8
Classifier: Programming Language :: Python :: 3.9
Requires-Python: >=3.7
Requires-Dist: numpy
Requires-Dist: transformers
Requires-Dist: datasets
Requires-Dist: fastcore
Provides-Extra: testing
Requires-Dist: pytest (>=6.0) ; extra == 'testing'
Requires-Dist: pytest-cov (>=2.0) ; extra == 'testing'
Requires-Dist: mypy (>=0.910) ; extra == 'testing'
Requires-Dist: flake8 (>=3.9) ; extra == 'testing'
Requires-Dist: tox (>=3.24) ; extra == 'testing'
